digi_connectcore_ble-1.0.7-py3.9-nspkg.pth
digi/ccble/__init__.py
digi/ccble/exceptions.py
digi/ccble/peripheral.py
digi/ccble/security.py
digi/ccble/service.py
digi/ccble/utils.py
digi_connectcore_ble-1.0.7.dist-info/LICENSE.txt
digi_connectcore_ble-1.0.7.dist-info/METADATA
digi_connectcore_ble-1.0.7.dist-info/WHEEL
digi_connectcore_ble-1.0.7.dist-info/namespace_packages.txt
digi_connectcore_ble-1.0.7.dist-info/top_level.txt
digi_connectcore_ble-1.0.7.dist-info/RECORD
