Metadata-Version: 2.1
Name: digi-connectcore-ble
Version: 1.0.7
Summary: Digi ConnectCore Bluetooth Low Energy library
Home-page: https://github.com/digi-embedded/connectcore-ble-python
Author: Digi International Inc.
Author-email: tech.support@digi.com
License: Mozilla Public License 2.0 (MPL 2.0)
Project-URL: Documentation, https://digi-connectcore-ble.readthedocs.io/en/latest/
Project-URL: Source, https://github.com/digi-embedded/connectcore-ble-python
Project-URL: Tracker, https://github.com/digi-embedded/connectcore-ble-python/issues
Keywords: bluetooth,connectcore,ble,digi,xbee
Classifier: Development Status :: 5 - Production/Stable
Classifier: Intended Audience :: Developers
Classifier: Intended Audience :: Telecommunications Industry
Classifier: Intended Audience :: End Users/Desktop
Classifier: Topic :: Software Development :: Libraries
Classifier: Topic :: Home Automation
Classifier: Topic :: Games/Entertainment
Classifier: License :: OSI Approved :: Mozilla Public License 2.0 (MPL 2.0)
Classifier: Programming Language :: Python
Classifier: Programming Language :: Python :: 3
Classifier: Programming Language :: Python :: 3.8
Classifier: Programming Language :: Python :: 3.9
Classifier: Programming Language :: Python :: 3.10
Classifier: Operating System :: OS Independent
Requires-Python: >=3, !=3.0.*, !=3.1.*, !=3.2.*, !=3.3.*, !=3.4.*, !=3.5.*, !=3.6.*, !=3.7.*
License-File: LICENSE.txt
Requires-Dist: bluezero ~=0.7.1
Requires-Dist: digi-xbee ~=1.4.1
Requires-Dist: pycairo ~=1.21.0
Requires-Dist: pycryptodome ~=3.15.0
Requires-Dist: pyserial ~=3.5
Requires-Dist: six ~=1.16.0
Requires-Dist: srp ~=1.0.19
Requires-Dist: dbus-python ~=1.2.18 ; platform_system != "Windows"
Requires-Dist: PyGObject ~=3.42.2 ; platform_system != "Windows"
